disco_oauth2/__init__.py
disco_oauth2/appinfo.py
disco_oauth2/client.py
disco_oauth2/connection.py
disco_oauth2/errors.py
disco_oauth2/flags.py
disco_oauth2/guild.py
disco_oauth2/http.py
disco_oauth2/integration.py
disco_oauth2/member.py
disco_oauth2/token.py
disco_oauth2/user.py
disco_oauth2/utils.py
disco_oauth2/types/__init__.py
disco_oauth2/types/appinfo.py
disco_oauth2/types/connection.py
disco_oauth2/types/guild.py
disco_oauth2/types/integration.py
disco_oauth2/types/member.py
disco_oauth2/types/snowflake.py
disco_oauth2/types/token.py
disco_oauth2/types/user.py
disco.oauth2-1.3b0.dist-info/LICENCE
disco.oauth2-1.3b0.dist-info/METADATA
disco.oauth2-1.3b0.dist-info/WHEEL
disco.oauth2-1.3b0.dist-info/top_level.txt
disco.oauth2-1.3b0.dist-info/RECORD
