Metadata-Version: 2.1
Name: disco.oauth2
Version: 1.3b0
Summary: An asynchronous discord OAuth2 API wrapper.
Home-page: https://github.com/InviteManagerBot/disco.oauth2
Author: martimartins
Author-email: martim13artins13@gmail.com
License: MIT
Classifier: License :: OSI Approved :: MIT License
Classifier: Programming Language :: Python :: 3
Classifier: Programming Language :: Python :: 3 :: Only
Classifier: Programming Language :: Python :: 3.10
Classifier: Programming Language :: Python :: 3.9
Classifier: Programming Language :: Python :: 3.8
Classifier: Programming Language :: Python :: Implementation :: CPython
Classifier: Intended Audience :: Developers
Classifier: Natural Language :: English
Classifier: Topic :: Internet
Classifier: Topic :: Software Development :: Libraries
Classifier: Topic :: Software Development :: Libraries :: Python Modules
Classifier: Topic :: Utilities
Classifier: Typing :: Typed
License-File: LICENCE
Requires-Dist: aiohttp (<4,>=3.7.4)
